nested_admin/__init__.py
nested_admin/compat.py
nested_admin/exceptions.py
nested_admin/forms.py
nested_admin/formsets.py
nested_admin/models.py
nested_admin/nested.py
nested_admin/polymorphic.py
nested_admin/urls.py
nested_admin/views.py
nested_admin/static/nested_admin/dist/nested_admin.css
nested_admin/static/nested_admin/dist/nested_admin.css.map
nested_admin/static/nested_admin/dist/nested_admin.js
nested_admin/static/nested_admin/dist/nested_admin.js.map
nested_admin/static/nested_admin/dist/nested_admin.min.css
nested_admin/static/nested_admin/dist/nested_admin.min.css.map
nested_admin/static/nested_admin/dist/nested_admin.min.js
nested_admin/static/nested_admin/dist/nested_admin.min.js.LICENSE.txt
nested_admin/static/nested_admin/dist/nested_admin.min.js.map
nested_admin/static/nested_admin/src/drag-handle.png
nested_admin/static/nested_admin/src/nested_admin.scss
nested_admin/static/nested_admin/src/nested-admin/django$.js
nested_admin/static/nested_admin/src/nested-admin/grp$.js
nested_admin/static/nested_admin/src/nested-admin/index.js
nested_admin/static/nested_admin/src/nested-admin/jquery.djangoformset.js
nested_admin/static/nested_admin/src/nested-admin/jquery.djnutils.js
nested_admin/static/nested_admin/src/nested-admin/jquery.shim.js
nested_admin/static/nested_admin/src/nested-admin/jquery.ui.djnsortable.js
nested_admin/static/nested_admin/src/nested-admin/jquery.ui.nestedsortable.js
nested_admin/static/nested_admin/src/nested-admin/regexquote.js
nested_admin/static/nested_admin/src/nested-admin/sortable.js
nested_admin/static/nested_admin/src/nested-admin/utils.js
nested_admin/templates/nesting/admin/includes/grappelli_inline.html
nested_admin/templates/nesting/admin/includes/grappelli_inline_tabular.html
nested_admin/templates/nesting/admin/includes/inline.html
nested_admin/templates/nesting/admin/inlines/grappelli_stacked.html
nested_admin/templates/nesting/admin/inlines/grappelli_tabular.html
django_nested_admin-4.1.6.dist-info/LICENSE
django_nested_admin-4.1.6.dist-info/METADATA
django_nested_admin-4.1.6.dist-info/WHEEL
django_nested_admin-4.1.6.dist-info/top_level.txt
django_nested_admin-4.1.6.dist-info/RECORD
