Metadata-Version: 2.1
Name: django-nested-admin
Version: 4.1.6
Summary: Django admin classes that allow for nested inlines
Home-page: https://github.com/theatlantic/django-nested-admin
Author: The Atlantic
Author-email: programmers@theatlantic.com
License: BSD
Platform: any
Classifier: Development Status :: 5 - Production/Stable
Classifier: Environment :: Web Environment
Classifier: Intended Audience :: Developers
Classifier: Operating System :: OS Independent
Classifier: Programming Language :: Python
Classifier: Programming Language :: Python :: 3
Classifier: Programming Language :: Python :: 3 :: Only
Classifier: Programming Language :: Python :: 3.7
Classifier: Programming Language :: Python :: 3.8
Classifier: Programming Language :: Python :: 3.9
Classifier: Programming Language :: Python :: 3.10
Classifier: Framework :: Django
Classifier: Framework :: Django :: 3.2
Classifier: Framework :: Django :: 4.0
Classifier: Framework :: Django :: 4.1
Requires-Python: >=3.6
License-File: LICENSE
Requires-Dist: python-monkey-business>=1.0.0
Provides-Extra: test
Requires-Dist: pytest; extra == "test"
Requires-Dist: pytest-cov; extra == "test"
Requires-Dist: pytest-xdist; extra == "test"
Requires-Dist: pytest-django; extra == "test"
Requires-Dist: Pillow; extra == "test"
Requires-Dist: dj-database-url; extra == "test"
Requires-Dist: django-selenosis; extra == "test"
Requires-Dist: selenium; extra == "test"
Provides-Extra: dev
Requires-Dist: black; extra == "dev"
Requires-Dist: flake8; extra == "dev"
Requires-Dist: pytest; extra == "dev"
Requires-Dist: pytest-cov; extra == "dev"
Requires-Dist: pytest-xdist; extra == "dev"
Requires-Dist: pytest-django; extra == "dev"
Requires-Dist: Pillow; extra == "dev"
Requires-Dist: dj-database-url; extra == "dev"
Requires-Dist: django-selenosis; extra == "dev"
Requires-Dist: selenium; extra == "dev"
